esrf_loadfile/__init__.py
esrf_loadfile/loadFile.py
esrf_loadfile-0.2.1.dist-info/licenses/LICENSE.md
esrf_loadfile-0.2.1.dist-info/METADATA
esrf_loadfile-0.2.1.dist-info/WHEEL
esrf_loadfile-0.2.1.dist-info/top_level.txt
esrf_loadfile-0.2.1.dist-info/RECORD
