Metadata-Version: 2.4
Name: esrf-loadfile
Version: 0.2.1
Summary: Generic loaders for ESRF useful files
Author-email: Charles ROMAIN <charles.romain@protonmail.com>
License: # MIT License
Project-URL: Homepage, https://gitlab.esrf.fr/graintracking/loadfile
Project-URL: Source, https://gitlab.esrf.fr/graintracking/loadfile
Project-URL: Issues, https://gitlab.esrf.fr/graintracking/loadfile/-/issues
Project-URL: Changelog, https://gitlab.esrf.fr/graintracking/loadfile/-/blob/main/CHANGELOG.md
Keywords: esrf,hdf5,tomography,diffraction,materials,loader
Classifier: Development Status :: 4 - Beta
Classifier: Intended Audience :: Science/Research
Classifier: License :: OSI Approved :: MIT License
Classifier: Operating System :: OS Independent
Classifier: Programming Language :: Python
Classifier: Programming Language :: Python :: 3
Classifier: Programming Language :: Python :: 3 :: Only
Classifier: Programming Language :: Python :: 3.10
Classifier: Programming Language :: Python :: 3.11
Classifier: Programming Language :: Python :: 3.12
Classifier: Topic :: Scientific/Engineering
Classifier: Topic :: Scientific/Engineering :: Information Analysis
Requires-Python: >=3.10
License-File: LICENSE.md
Requires-Dist: h5py
Requires-Dist: numpy
Requires-Dist: scipy
Requires-Dist: silx
Requires-Dist: esrf-pathlib>=0.5.0
Provides-Extra: test
Requires-Dist: pytest; extra == "test"
Requires-Dist: pytest-cov; extra == "test"
Requires-Dist: pytest-mock; extra == "test"
Requires-Dist: pytest-profiling!=1.8.0; extra == "test"
Requires-Dist: pytest-rerunfailures; extra == "test"
Requires-Dist: pytest-xvfb; extra == "test"
Provides-Extra: dev
Requires-Dist: bandit; extra == "dev"
Requires-Dist: black; extra == "dev"
Requires-Dist: build; extra == "dev"
Requires-Dist: flake8; extra == "dev"
Requires-Dist: flake8-pep585; extra == "dev"
Requires-Dist: mypy>=1.8.0; extra == "dev"
Requires-Dist: pre-commit; extra == "dev"
Requires-Dist: ruff>=0.4.0; extra == "dev"
Requires-Dist: scriv>=1.3.1; extra == "dev"
Requires-Dist: twine; extra == "dev"
Requires-Dist: pytest; extra == "dev"
Requires-Dist: pytest-cov; extra == "dev"
Requires-Dist: pytest-mock; extra == "dev"
Requires-Dist: pytest-profiling!=1.8.0; extra == "dev"
Requires-Dist: pytest-rerunfailures; extra == "dev"
Requires-Dist: pytest-xvfb; extra == "dev"
Dynamic: license-file
